setup.py
flask_sqlalchemy_raw/__init__.py
flask_sqlalchemy_raw.egg-info/PKG-INFO
flask_sqlalchemy_raw.egg-info/SOURCES.txt
flask_sqlalchemy_raw.egg-info/dependency_links.txt
flask_sqlalchemy_raw.egg-info/requires.txt
flask_sqlalchemy_raw.egg-info/top_level.txt