Metadata-Version: 1.0
Name: flask-sqlalchemy-raw
Version: 0.0.4
Summary: flask_sqlalchemy execute raw sql
Home-page: UNKNOWN
Author: UNKNOWN
Author-email: UNKNOWN
License: UNKNOWN
Platform: UNKNOWN
